{
    "login": "LucasAlderfer",
    "id": 36676968,
    "node_id": "MDQ6VXNlcjM2Njc2OTY4",
    "avatar_url": "https://avatars1.githubusercontent.com/u/36676968?v=4",
    "gravatar_id": "",
    "url": "https://api.github.com/users/LucasAlderfer",
    "html_url": "https://github.com/LucasAlderfer",
    "followers_url": "https://api.github.com/users/LucasAlderfer/followers",
    "following_url": "https://api.github.com/users/LucasAlderfer/following{/other_user}",
    "gists_url": "https://api.github.com/users/LucasAlderfer/gists{/gist_id}",
    "starred_url": "https://api.github.com/users/LucasAlderfer/starred{/owner}{/repo}",
    "subscriptions_url": "https://api.github.com/users/LucasAlderfer/subscriptions",
    "organizations_url": "https://api.github.com/users/LucasAlderfer/orgs",
    "repos_url": "https://api.github.com/users/LucasAlderfer/repos",
    "events_url": "https://api.github.com/users/LucasAlderfer/events{/privacy}",
    "received_events_url": "https://api.github.com/users/LucasAlderfer/received_events",
    "type": "User",
    "site_admin": false,
    "name": "Lucas Alderfer",
    "company": null,
    "blog": "",
    "location": null,
    "email": null,
    "hireable": null,
    "bio": null,
    "public_repos": 39,
    "public_gists": 4,
    "followers": 3,
    "following": 1,
    "created_at": "2018-02-20T19:27:43Z",
    "updated_at": "2018-08-22T14:57:11Z",
    "private_gists": 6,
    "total_private_repos": 0,
    "owned_private_repos": 0,
    "disk_usage": 28666,
    "collaborators": 0,
    "two_factor_authentication": false,
    "plan": {
        "name": "free",
        "space": 976562499,
        "collaborators": 0,
        "private_repos": 0
    }
}
